qrs/__init__.py
qrs/__main__.py
qrs/ext.py
qrs/letter_scores.json
qrs/wordlist.txt
qrs-3.0.0.dist-info/LICENSE
qrs-3.0.0.dist-info/METADATA
qrs-3.0.0.dist-info/WHEEL
qrs-3.0.0.dist-info/entry_points.txt
qrs-3.0.0.dist-info/top_level.txt
qrs-3.0.0.dist-info/zip-safe
qrs-3.0.0.dist-info/RECORD
