Metadata-Version: 2.1
Name: qrs
Version: 3.0.0
Summary: Provides word game-related tools that can be configured with custom settings, letter scores, and wordlists. 
Home-page: https://github.com/silvncr/qrs
Author: silvncr
License: MIT
Classifier: Development Status :: 5 - Production/Stable
Classifier: Intended Audience :: Developers
Classifier: Intended Audience :: Education
Classifier: Intended Audience :: End Users/Desktop
Classifier: License :: OSI Approved :: MIT License
Classifier: Natural Language :: English
Classifier: Operating System :: OS Independent
Classifier: Topic :: Games/Entertainment :: Board Games
Classifier: Topic :: Games/Entertainment :: Puzzle Games
Requires-Python: >=3.8
License-File: LICENSE
Requires-Dist: jarguments==0.3.0
